json_ld_test/__init__.py
json_ld_test/codegen.py
json_ld_test/load.py
json_ld_test/models.py
json_ld_test-0.0.1.dist-info/METADATA
json_ld_test-0.0.1.dist-info/WHEEL
json_ld_test-0.0.1.dist-info/top_level.txt
json_ld_test-0.0.1.dist-info/RECORD
