Metadata-Version: 2.1
Name: json-ld-test
Version: 0.0.1
Summary: The official JSON-LD test suite as a Python package.
Author-email: Michael Milton <michael.r.milton@gmail.com>
License: MIT License
Requires-Python: >=3.9
Requires-Dist: linkml-runtime>=1.8.3
Requires-Dist: pydantic
Provides-Extra: dev
Requires-Dist: requests; extra == "dev"
Requires-Dist: pytest; extra == "dev"
Requires-Dist: linkml-runtime>=1.8.3; extra == "dev"
Requires-Dist: linkml>=1.8.5; extra == "dev"
Requires-Dist: mkdocs-material>=9.5.48; extra == "dev"
Requires-Dist: mkdocs>=1.6.1; extra == "dev"
Requires-Dist: mkdocstrings[python]>=0.27.0; extra == "dev"
Requires-Dist: griffe-pydantic>=1.1.0; extra == "dev"
